gc_qdk/__init__.py
gc_qdk/cfg.py
gc_qdk/main.py
gc_qdk-0.0.4.dist-info/METADATA
gc_qdk-0.0.4.dist-info/WHEEL
gc_qdk-0.0.4.dist-info/top_level.txt
gc_qdk-0.0.4.dist-info/RECORD
