Metadata-Version: 2.1
Name: gc-qdk
Version: 0.0.4
Summary: GCQDK - SDK для работы с API GCore Compound.
Home-page: UNKNOWN
Author: Arthur
Author-email: ksmdrmvstchny@gmail.com
License: MIT
Platform: UNKNOWN
Requires-Dist: qdk
Requires-Dist: psycopg2
